auth0rization/__init__.py
auth0rization/access.py
auth0rization/common.py
auth0rization/errors.py
auth0rization/keyset.py
auth0rization/validator.py
auth0rization-1.0.0.dist-info/METADATA
auth0rization-1.0.0.dist-info/WHEEL
auth0rization-1.0.0.dist-info/licenses/LICENSE
auth0rization-1.0.0.dist-info/RECORD
