Metadata-Version: 2.1
Name: auth0rization
Version: 1.0.0
Summary: A package to perform actions related to auth0 JWT tokens.
Project-URL: Homepage, https://github.com/nbiegel/auth0rization-python
Project-URL: Bug Tracker, https://github.com/nbiegel/auth0rization-python/issues
Author-email: Nicholas Biegel <contact@nbiegel.com>
License: MIT License
Classifier: Intended Audience :: Developers
Classifier: License :: OSI Approved :: MIT License
Classifier: Natural Language :: English
Classifier: Programming Language :: Python :: 3.10
Classifier: Programming Language :: Python :: 3.6
Classifier: Programming Language :: Python :: 3.7
Classifier: Programming Language :: Python :: 3.8
Classifier: Programming Language :: Python :: 3.9
Classifier: Topic :: Security
Classifier: Topic :: Software Development :: Libraries :: Python Modules
Requires-Python: >=3.6
Requires-Dist: jwcrypto>=1.0
Requires-Dist: requests>=2.27.1
Provides-Extra: dev
Requires-Dist: build; extra == 'dev'
Requires-Dist: coverage; extra == 'dev'
Requires-Dist: pylint; extra == 'dev'
Requires-Dist: twine; extra == 'dev'
